pykeyence_plc_link/__init__.py
pykeyence_plc_link/client.py
pykeyence_plc_link/data.py
pykeyence_plc_link/heartbeat.py
pykeyence_plc_link/monitor.py
pykeyence_plc_link/protocol.py
pykeyence_plc_link/mock/mock_keyence_plc_server.py
pykeyence-0.1.12.dist-info/METADATA
pykeyence-0.1.12.dist-info/WHEEL
pykeyence-0.1.12.dist-info/top_level.txt
pykeyence-0.1.12.dist-info/RECORD
